cpu/riscv5stagedemo/IMM_GEN/imm_gen.v
// ============================================================================
// IMM_GEN.v - RISC-V Immediate Generator
// ============================================================================
// Mô tả: Trích xuất và sign-extend immediate từ instruction
// Hỗ trợ: I-type, S-type, B-type, U-type, J-type
// ============================================================================

module imm_gen (
    input wire [31:0] instr,        // Instruction 32-bit
    output reg [31:0] imm           // Immediate value (sign-extended)
);

    // ========================================================================
    // RISC-V Opcode Definition
    // ========================================================================
    localparam [6:0]
        OP_R_TYPE   = 7'b0110011,    // R-type (không có immediate)
        OP_I_TYPE   = 7'b0010011,    // I-type: ADDI, ANDI, ORI, etc.
        OP_LOAD     = 7'b0000011,    // I-type: LW, LH, LB
        OP_JALR     = 7'b1100111,    // I-type: JALR
        OP_STORE    = 7'b0100011,    // S-type: SW, SH, SB
        OP_BRANCH   = 7'b1100011,    // B-type: BEQ, BNE, BLT, etc.
        OP_LUI      = 7'b0110111,    // U-type: LUI
        OP_AUIPC    = 7'b0010111,    // U-type: AUIPC
        OP_JAL      = 7'b1101111;    // J-type: JAL
    
    wire [6:0] opcode = instr[6:0];
    
    // ========================================================================
    // Immediate Generation Logic
    // ========================================================================
    always @(*) begin
        case (opcode)
            // ================================================================
            // I-TYPE: 12-bit immediate
            // Format: imm[11:0] = instr[31:20]
            // Sign-extend từ bit 31
            // ================================================================
            OP_I_TYPE, OP_LOAD, OP_JALR: begin
                imm = {{20{instr[31]}}, instr[31:20]};
            end
            
            // ================================================================
            // S-TYPE: Store instructions (12-bit immediate)
            // Format: imm[11:5] = instr[31:25], imm[4:0] = instr[11:7]
            // Sign-extend từ bit 31
            // ================================================================
            OP_STORE: begin
                imm = {{20{instr[31]}}, instr[31:25], instr[11:7]};
            end
            
            // ================================================================
            // B-TYPE: Branch instructions (13-bit immediate, always even)
            // Format: imm[12] = instr[31]
            //         imm[11] = instr[7]
            //         imm[10:5] = instr[30:25]
            //         imm[4:1] = instr[11:8]
            //         imm[0] = 0 (luôn chẵn)
            // Sign-extend từ bit 31
            // ================================================================
            OP_BRANCH: begin
                imm = {{19{instr[31]}}, instr[31], instr[7], instr[30:25], instr[11:8], 1'b0};
            end
            
            // ================================================================
            // U-TYPE: Upper immediate (20-bit immediate)
            // Format: imm[31:12] = instr[31:12], imm[11:0] = 0
            // Dùng cho LUI và AUIPC
            // ================================================================
            OP_LUI, OP_AUIPC: begin
                imm = {instr[31:12], 12'b0};
            end
            
            // ================================================================
            // J-TYPE: Jump (JAL) (21-bit immediate, always even)
            // Format: imm[20] = instr[31]
            //         imm[19:12] = instr[19:12]
            //         imm[11] = instr[20]
            //         imm[10:1] = instr[30:21]
            //         imm[0] = 0 (luôn chẵn)
            // Sign-extend từ bit 31
            // ================================================================
            OP_JAL: begin
                imm = {{11{instr[31]}}, instr[31], instr[19:12], instr[20], instr[30:21], 1'b0};
            end
            
            // ================================================================
            // R-TYPE và các opcode khác: không có immediate
            // ================================================================
            default: begin
                imm = 32'h00000000;
            end
        endcase
    end

endmodule

cpu/riscv5stagedemo/IMM_GEN/tb_imm_gen.v
// ============================================================================
// IMM_GEN_tb.v - Testbench cho RISC-V Immediate Generator
// ============================================================================

`timescale 1ns/1ps
`include "imm_gen.v"
module tb_imm_gen;

    // Tín hiệu
    reg [31:0] instr;
    wire [31:0] imm;
    
    // Biến đếm test
    integer passed, failed;
    
    // Opcode định nghĩa
    localparam [6:0]
        OP_R_TYPE   = 7'b0110011,
        OP_I_TYPE   = 7'b0010011,
        OP_LOAD     = 7'b0000011,
        OP_JALR     = 7'b1100111,
        OP_STORE    = 7'b0100011,
        OP_BRANCH   = 7'b1100011,
        OP_LUI      = 7'b0110111,
        OP_AUIPC    = 7'b0010111,
        OP_JAL      = 7'b1101111;
    
    // Khởi tạo DUT
    imm_gen uut (
        .instr(instr),
        .imm(imm)
    );
    
    // Task để kiểm tra kết quả
    task check_immediate;
        input [31:0] expected;
        input [200*8:1] test_name;
        begin
            #1;
            if (imm === expected) begin
                $display("  ✓ PASS: %0s", test_name);
                $display("      Instruction: 0x%h", instr);
                $display("      Immediate:   0x%h (dec: %0d)", imm, $signed(imm));
                passed = passed + 1;
            end
            else begin
                $display("  ✗ FAIL: %0s", test_name);
                $display("      Instruction: 0x%h", instr);
                $display("      Expected:    0x%h (dec: %0d)", expected, $signed(expected));
                $display("      Got:         0x%h (dec: %0d)", imm, $signed(imm));
                failed = failed + 1;
            end
            $display("");
        end
    endtask
    
    // Test sequence
    initial begin
        $dumpfile("tb_imm_gen.vcd");
        $dumpvars(0, tb_imm_gen);
        
        passed = 0;
        failed = 0;
        instr = 0;
        
        $display("\n============================================");
        $display("  RISC-V Immediate Generator Testbench");
        $display("============================================\n");
        
        // ================================================================
        // TEST 1: I-Type Instructions (12-bit immediate)
        // ================================================================
        $display("[TEST 1] I-Type Instructions (12-bit immediate)\n");
        
        // ADDI x5, x0, 100
        // Format: imm[11:0] | rs1 | 000 | rd | 0010011
        // imm = 100 = 0x064
        instr = {12'd100, 5'd0, 3'b000, 5'd5, OP_I_TYPE};
        check_immediate(32'd100, "ADDI with positive immediate (100)");
        
        // ADDI x5, x0, -50
        // imm = -50 = 0xFCE (12-bit two's complement)
        instr = {12'hFCE, 5'd0, 3'b000, 5'd5, OP_I_TYPE};
        check_immediate(32'hFFFFFFCE, "ADDI with negative immediate (-50)");
        
        // ADDI x5, x0, 2047 (max positive)
        instr = {12'd2047, 5'd0, 3'b000, 5'd5, OP_I_TYPE};
        check_immediate(32'd2047, "ADDI with max positive (2047)");
        
        // ADDI x5, x0, -2048 (min negative)
        instr = {12'h800, 5'd0, 3'b000, 5'd5, OP_I_TYPE};
        check_immediate(32'hFFFFF800, "ADDI with min negative (-2048)");
        
        // LW x10, 20(x2)
        // imm = 20
        instr = {12'd20, 5'd2, 3'b010, 5'd10, OP_LOAD};
        check_immediate(32'd20, "LW with offset 20");
        
        // JALR x1, x5, -4
        instr = {12'hFFC, 5'd5, 3'b000, 5'd1, OP_JALR};
        check_immediate(32'hFFFFFFFC, "JALR with offset -4");
        
        // ================================================================
        // TEST 2: S-Type Instructions (12-bit immediate)
        // ================================================================
        $display("[TEST 2] S-Type Instructions (12-bit immediate)\n");
        
        // SW x10, 40(x2)
        // Format: imm[11:5] | rs2 | rs1 | 010 | imm[4:0] | 0100011
        // imm = 40 = 0x028
        instr = {7'b0000001, 5'd10, 5'd2, 3'b010, 5'b01000, OP_STORE};
        check_immediate(32'd40, "SW with offset 40");
        
        // SW x15, -8(x3)
        // imm = -8 = 0xFF8 (12-bit)
        instr = {7'b1111111, 5'd15, 5'd3, 3'b010, 5'b11000, OP_STORE};
        check_immediate(32'hFFFFFFF8, "SW with negative offset -8");
        
        // SH x7, 100(x4)
        // imm = 100 = 0x064
        instr = {7'b0000011, 5'd7, 5'd4, 3'b001, 5'b00100, OP_STORE};
        check_immediate(32'd100, "SH with offset 100");
        
        // SB x8, -1(x5)
        // imm = -1 = 0xFFF (12-bit)
        instr = {7'b1111111, 5'd8, 5'd5, 3'b000, 5'b11111, OP_STORE};
        check_immediate(32'hFFFFFFFF, "SB with offset -1");
        
        // ================================================================
        // TEST 3: B-Type Instructions (13-bit immediate, always even)
        // ================================================================
        $display("[TEST 3] B-Type Instructions (13-bit immediate)\n");
        
        // BEQ x5, x6, 8
        // Format: imm[12|10:5] | rs2 | rs1 | 000 | imm[4:1|11] | 1100011
        // imm = 8 = 0b0000_0000_1000
        // imm[12] = 0, imm[11] = 0, imm[10:5] = 000000, imm[4:1] = 0100
        instr = {1'b0, 6'b000000, 5'd6, 5'd5, 3'b000, 4'b0100, 1'b0, OP_BRANCH};
        check_immediate(32'd8, "BEQ with offset 8");
        
        // BNE x7, x8, -4
        // imm = -4 = 0b1_1111_1111_1100 (13-bit)
        instr = {1'b1, 6'b111111, 5'd8, 5'd7, 3'b001, 4'b1110, 1'b1, OP_BRANCH};
        check_immediate(32'hFFFFFFFC, "BNE with offset -4");
        
        // BLT x1, x2, 16
        // imm = 16 = 0x010
        instr = {1'b0, 6'b000000, 5'd2, 5'd1, 3'b100, 4'b1000, 1'b0, OP_BRANCH};
        check_immediate(32'd16, "BLT with offset 16");
        
        // BGE x3, x4, -12
        // -12 in decimal = ...11110100 in binary
        // As 13-bit immediate (with bit 0 implicit 0): 1_111111_1101_0
        // Wait, let me recalculate: -12 / 2 = -6 (since bit 0 is implicit)
        // But actually: -12 = 0b1111_1111_1111_1111_1111_1111_1111_0100 (32-bit)
        // Take bits [12:1] for B-type (bit 0 is implicit 0):
        // Bits [12:1] of -12 = bits [12:1] of 0xFFFFFFF4
        // 0xFFFFFFF4 >> 1 = 0xFFFFFFFA, take low 12 bits = 0xFFA = 1111_1111_1010
        // So: imm[12:1] = 1_1111_1111_010
        // imm[12]=1, imm[11]=1, imm[10:5]=111111, imm[4:1]=1010
        // B-type format: imm[12] imm[10:5] rs2 rs1 funct3 imm[4:1] imm[11] opcode
        instr = {1'b1, 6'b111111, 5'd4, 5'd3, 3'b101, 4'b1010, 1'b1, OP_BRANCH};
        check_immediate(32'hFFFFFFF4, "BGE with offset -12");
        
        // ================================================================
        // TEST 4: U-Type Instructions (20-bit immediate)
        // ================================================================
        $display("[TEST 4] U-Type Instructions (20-bit immediate)\n");
        
        // LUI x10, 0x12345
        // Format: imm[31:12] | rd | 0110111
        // Result: 0x12345000
        instr = {20'h12345, 5'd10, OP_LUI};
        check_immediate(32'h12345000, "LUI with 0x12345");
        
        // LUI x5, 0xFFFFF (max value)
        instr = {20'hFFFFF, 5'd5, OP_LUI};
        check_immediate(32'hFFFFF000, "LUI with 0xFFFFF");
        
        // AUIPC x7, 0x10000
        instr = {20'h10000, 5'd7, OP_AUIPC};
        check_immediate(32'h10000000, "AUIPC with 0x10000");
        
        // AUIPC x8, 0x00001
        instr = {20'h00001, 5'd8, OP_AUIPC};
        check_immediate(32'h00001000, "AUIPC with 0x00001");
        
        // ================================================================
        // TEST 5: J-Type Instructions (21-bit immediate, always even)
        // ================================================================
        $display("[TEST 5] J-Type Instructions (21-bit immediate)\n");
        
        // JAL x1, 20
        // Format: imm[20|10:1|11|19:12] | rd | 1101111
        // imm = 20 = 0b0_0000_0000_0000_0001_0100
        // imm[20] = 0, imm[19:12] = 00000000, imm[11] = 0, imm[10:1] = 0000001010
        instr = {1'b0, 10'b0000001010, 1'b0, 8'b00000000, 5'd1, OP_JAL};
        check_immediate(32'd20, "JAL with offset 20");
        
        // JAL x5, -8
        // imm = -8 = 0b1_1111_1111_1111_1111_1000 (21-bit)
        instr = {1'b1, 10'b1111111100, 1'b1, 8'b11111111, 5'd5, OP_JAL};
        check_immediate(32'hFFFFFFF8, "JAL with offset -8");
        
        // JAL x10, 1024
        // imm = 1024 (decimal) = 0x400 = 0b010_0000_0000 (bit 10 is set)
        // Immediate bits: imm[20:1] (imm[0] is implicit 0)
        // imm[10]=1, all other bits=0
        // Encoding in instruction:
        //   instr[31] = imm[20] = 0
        //   instr[30:21] = imm[10:1] = 10_0000_0000 (bit position 30 = imm[10] = 1)
        //   instr[20] = imm[11] = 0
        //   instr[19:12] = imm[19:12] = 00000000
        // J-type format: imm[20] imm[10:1] imm[11] imm[19:12] rd opcode
        instr = {1'b0, 10'b1000000000, 1'b0, 8'b00000000, 5'd10, OP_JAL};
        check_immediate(32'd1024, "JAL with offset 1024");
        
        // JAL x15, -2048
        // imm = -2048 = 0x800 (in 21-bit)
        instr = {1'b1, 10'b0000000000, 1'b1, 8'b11111111, 5'd15, OP_JAL};
        check_immediate(32'hFFFFF800, "JAL with offset -2048");
        
        // ================================================================
        // TEST 6: R-Type (no immediate)
        // ================================================================
        $display("[TEST 6] R-Type Instructions (no immediate)\n");
        
        // ADD x5, x6, x7
        instr = {7'b0000000, 5'd7, 5'd6, 3'b000, 5'd5, OP_R_TYPE};
        check_immediate(32'h00000000, "ADD (R-type, no immediate)");
        
        // SUB x10, x11, x12
        instr = {7'b0100000, 5'd12, 5'd11, 3'b000, 5'd10, OP_R_TYPE};
        check_immediate(32'h00000000, "SUB (R-type, no immediate)");
        
        // ================================================================
        // TEST 7: Edge Cases
        // ================================================================
        $display("[TEST 7] Edge Cases\n");
        
        // Tất cả bit 1 trong immediate field (I-type)
        instr = {12'hFFF, 5'd0, 3'b000, 5'd5, OP_I_TYPE};
        check_immediate(32'hFFFFFFFF, "I-type with all 1s (-1)");
        
        // Immediate = 0
        instr = {12'h000, 5'd0, 3'b000, 5'd5, OP_I_TYPE};
        check_immediate(32'h00000000, "I-type with immediate = 0");
        
        // ================================================================
        // Kết quả
        // ================================================================
        #10;
        $display("\n============================================");
        $display("  Testbench Summary");
        $display("============================================");
        $display("  Total tests: %0d", passed + failed);
        $display("  ✓ Passed: %0d", passed);
        $display("  ✗ Failed: %0d", failed);
        
        if (failed == 0) begin
            $display("\n  🎉 ALL TESTS PASSED! 🎉");
        end else begin
            $display("\n  ⚠️  SOME TESTS FAILED");
        end
        $display("============================================\n");
        
        $finish;
    end

endmodule

cpu/riscv5stagedemo/IMM_GEN/tb_imm_gen.vcd
$date
	Sun Nov 02 14:17:37 2025
$end
$version
	Icarus Verilog
$end
$timescale
	1ps
$end
$scope module tb_imm_gen $end
$var wire 32 ! imm [31:0] $end
$var parameter 7 " OP_AUIPC $end
$var parameter 7 # OP_BRANCH $end
$var parameter 7 $ OP_I_TYPE $end
$var parameter 7 % OP_JAL $end
$var parameter 7 & OP_JALR $end
$var parameter 7 ' OP_LOAD $end
$var parameter 7 ( OP_LUI $end
$var parameter 7 ) OP_R_TYPE $end
$var parameter 7 * OP_STORE $end
$var reg 32 + instr [31:0] $end
$var integer 32 , failed [31:0] $end
$var integer 32 - passed [31:0] $end
$scope module uut $end
$var wire 32 . instr [31:0] $end
$var wire 7 / opcode [6:0] $end
$var parameter 7 0 OP_AUIPC $end
$var parameter 7 1 OP_BRANCH $end
$var parameter 7 2 OP_I_TYPE $end
$var parameter 7 3 OP_JAL $end
$var parameter 7 4 OP_JALR $end
$var parameter 7 5 OP_LOAD $end
$var parameter 7 6 OP_LUI $end
$var parameter 7 7 OP_R_TYPE $end
$var parameter 7 8 OP_STORE $end
$var reg 32 9 imm [31:0] $end
$upscope $end
$scope task check_immediate $end
$var reg 32 : expected [31:0] $end
$var reg 1600 ; test_name [1600:1] $end
$upscope $end
$upscope $end
$enddefinitions $end
$comment Show the parameter values. $end
$dumpall
b100011 8
b110011 7
b110111 6
b11 5
b1100111 4
b1101111 3
b10011 2
b1100011 1
b10111 0
b100011 *
b110011 )
b110111 (
b11 '
b1100111 &
b1101111 %
b10011 $
b1100011 #
b10111 "
$end
#0
$dumpvars
b1000001010001000100010001001001001000000111011101101001011101000110100000100000011100000110111101110011011010010111010001101001011101100110010100100000011010010110110101101101011001010110010001101001011000010111010001100101001000000010100000110001001100000011000000101001 ;
b1100100 :
b1100100 9
b10011 /
b110010000000000001010010011 .
b0 -
b0 ,
b110010000000000001010010011 +
b1100100 !
$end
#1000
b11111111111111111111111111001110 !
b11111111111111111111111111001110 9
b1000001010001000100010001001001001000000111011101101001011101000110100000100000011011100110010101100111011000010111010001101001011101100110010100100000011010010110110101101101011001010110010001101001011000010111010001100101001000000010100000101101001101010011000000101001 ;
b11111111111111111111111111001110 :
b11111100111000000000001010010011 +
b11111100111000000000001010010011 .
b1 -
#2000
b11111111111 !
b11111111111 9
b100000101000100010001000100100100100000011101110110100101110100011010000010000001101101011000010111100000100000011100000110111101110011011010010111010001101001011101100110010100100000001010000011001000110000001101000011011100101001 ;
b11111111111 :
b1111111111100000000001010010011 +
b1111111111100000000001010010011 .
b10 -
#3000
b11111111111111111111100000000000 !
b11111111111111111111100000000000 9
b10000010100010001000100010010010010000001110111011010010111010001101000001000000110110101101001011011100010000001101110011001010110011101100001011101000110100101110110011001010010000000101000001011010011001000110000001101000011100000101001 ;
b11111111111111111111100000000000 :
b10000000000000000000001010010011 +
b10000000000000000000001010010011 .
b11 -
#4000
b10100 !
b10100 9
b11 /
b100110001010111001000000111011101101001011101000110100000100000011011110110011001100110011100110110010101110100001000000011001000110000 ;
b10100 :
b1010000010010010100000011 +
b1010000010010010100000011 .
b100 -
#5000
b11111111111111111111111111111100 !
b11111111111111111111111111111100 9
b1100111 /
b1001010010000010100110001010010001000000111011101101001011101000110100000100000011011110110011001100110011100110110010101110100001000000010110100110100 ;
b11111111111111111111111111111100 :
b11111111110000101000000011100111 +
b11111111110000101000000011100111 .
b101 -
#6000
b101000 !
b101000 9
b100011 /
b101001101010111001000000111011101101001011101000110100000100000011011110110011001100110011100110110010101110100001000000011010000110000 ;
b101000 :
b10101000010010010000100011 +
b10101000010010010000100011 .
b110 -
#7000
b11111111111111111111111111111000 !
b11111111111111111111111111111000 9
b101001101010111001000000111011101101001011101000110100000100000011011100110010101100111011000010111010001101001011101100110010100100000011011110110011001100110011100110110010101110100001000000010110100111000 ;
b11111111111111111111111111111000 :
b11111110111100011010110000100011 +
b11111110111100011010110000100011 .
b111 -
#8000
b1100100 !
b1100100 9
b10100110100100000100000011101110110100101110100011010000010000001101111011001100110011001110011011001010111010000100000001100010011000000110000 ;
b1100100 :
b110011100100001001000100011 +
b110011100100001001000100011 .
b1000 -
#9000
b11111111111111111111111111111111 !
b11111111111111111111111111111111 9
b101001101000010001000000111011101101001011101000110100000100000011011110110011001100110011100110110010101110100001000000010110100110001 ;
b11111111111111111111111111111111 :
b11111110100000101000111110100011 +
b11111110100000101000111110100011 .
b1001 -
#10000
b1000 !
b1000 9
b1100011 /
b100001001000101010100010010000001110111011010010111010001101000001000000110111101100110011001100111001101100101011101000010000000111000 ;
b1000 :
b11000101000010001100011 +
b11000101000010001100011 .
b1010 -
#11000
b11111111111111111111111111111100 !
b11111111111111111111111111111100 9
b10000100100111001000101001000000111011101101001011101000110100000100000011011110110011001100110011100110110010101110100001000000010110100110100 ;
b11111111111111111111111111111100 :
b11111110100000111001111011100011 +
b11111110100000111001111011100011 .
b1011 -
#12000
b10000 !
b10000 9
b10000100100110001010100001000000111011101101001011101000110100000100000011011110110011001100110011100110110010101110100001000000011000100110110 ;
b10000 :
b1000001100100001100011 +
b1000001100100001100011 .
b1100 -
#13000
b11111111111111111111111111110100 !
b11111111111111111111111111110100 9
b1000010010001110100010100100000011101110110100101110100011010000010000001101111011001100110011001110011011001010111010000100000001011010011000100110010 ;
b11111111111111111111111111110100 :
b11111110010000011101101011100011 +
b11111110010000011101101011100011 .
b1101 -
#14000
b10010001101000101000000000000 !
b10010001101000101000000000000 9
b110111 /
b1001100010101010100100100100000011101110110100101110100011010000010000000110000011110000011000100110010001100110011010000110101 ;
b10010001101000101000000000000 :
b10010001101000101010100110111 +
b10010001101000101010100110111 .
b1110 -
#15000
b11111111111111111111000000000000 !
b11111111111111111111000000000000 9
b1001100010101010100100100100000011101110110100101110100011010000010000000110000011110000100011001000110010001100100011001000110 ;
b11111111111111111111000000000000 :
b11111111111111111111001010110111 +
b11111111111111111111001010110111 .
b1111 -
#16000
b10000000000000000000000000000 !
b10000000000000000000000000000 9
b10111 /
b10000010101010101001001010100000100001100100000011101110110100101110100011010000010000000110000011110000011000100110000001100000011000000110000 ;
b10000000000000000000000000000 :
b10000000000000000001110010111 +
b10000000000000000001110010111 .
b10000 -
#17000
b1000000000000 !
b1000000000000 9
b10000010101010101001001010100000100001100100000011101110110100101110100011010000010000000110000011110000011000000110000001100000011000000110001 ;
b1000000000000 :
b1010000010111 +
b1010000010111 .
b10001 -
#18000
b10100 !
b10100 9
b1101111 /
b10010100100000101001100001000000111011101101001011101000110100000100000011011110110011001100110011100110110010101110100001000000011001000110000 ;
b10100 :
b1010000000000000011101111 +
b1010000000000000011101111 .
b10010 -
#19000
b11111111111111111111111111111000 !
b11111111111111111111111111111000 9
b10010100100000101001100001000000111011101101001011101000110100000100000011011110110011001100110011100110110010101110100001000000010110100111000 ;
b11111111111111111111111111111000 :
b11111111100111111111001011101111 +
b11111111100111111111001011101111 .
b10011 -
#20000
b10000000000 !
b10000000000 9
b100101001000001010011000010000001110111011010010111010001101000001000000110111101100110011001100111001101100101011101000010000000110001001100000011001000110100 ;
b10000000000 :
b1000000000000000000010101101111 +
b1000000000000000000010101101111 .
b10100 -
#21000
b11111111111111111111100000000000 !
b11111111111111111111100000000000 9
b10010100100000101001100001000000111011101101001011101000110100000100000011011110110011001100110011100110110010101110100001000000010110100110010001100000011010000111000 ;
b11111111111111111111100000000000 :
b10000000000111111111011111101111 +
b10000000000111111111011111101111 .
b10101 -
#22000
b0 !
b0 9
b110011 /
b100000101000100010001000010000000101000010100100010110101110100011110010111000001100101001011000010000001101110011011110010000001101001011011010110110101100101011001000110100101100001011101000110010100101001 ;
b0 :
b11100110000001010110011 +
b11100110000001010110011 .
b10110 -
#23000
b101001101010101010000100010000000101000010100100010110101110100011110010111000001100101001011000010000001101110011011110010000001101001011011010110110101100101011001000110100101100001011101000110010100101001 ;
b1000000110001011000010100110011 +
b1000000110001011000010100110011 .
b10111 -
#24000
b11111111111111111111111111111111 !
b11111111111111111111111111111111 9
b10011 /
b100100100101101011101000111100101110000011001010010000001110111011010010111010001101000001000000110000101101100011011000010000000110001011100110010000000101000001011010011000100101001 ;
b11111111111111111111111111111111 :
b11111111111100000000001010010011 +
b11111111111100000000001010010011 .
b11000 -
#25000
b0 !
b0 9
b1001001001011010111010001111001011100000110010100100000011101110110100101110100011010000010000001101001011011010110110101100101011001000110100101100001011101000110010100100000001111010010000000110000 ;
b0 :
b1010010011 +
b1010010011 .
b11001 -
#26000
b11010 -
