cpu/riscv5stagedemo/IFU/inst_mem.v
// ============================================================================
// Module: INST_MEM - Bộ nhớ lệnh (ROM)
// Mô tả: Bộ nhớ chỉ đọc lưu trữ chương trình RISC-V 32IM
// Tương thích: Icarus Verilog simulation & OpenLane synthesis
// ============================================================================

module inst_mem (
    input  [31:0] PC,                  // Program Counter - địa chỉ byte hiện tại

    output [31:0] Instruction_Code     // Lệnh 32-bit đọc ra
);

    // ========================================================================
    // Khai báo bộ nhớ: 1024 từ x 32 bit = 4096 byte = 4KB
    // ========================================================================
    reg [31:0] memory [0:1023];
    
    // ========================================================================
    // Tính địa chỉ từ (word address) từ địa chỉ byte
    // PC là địa chỉ byte, cần chia 4 để lấy địa chỉ từ (word-aligned)
    // PC[11:2] tương đương PC >> 2 (dịch phải 2 bit)
    // ========================================================================
    wire [9:0] word_addr;              // Địa chỉ từ 10-bit (0 đến 1023)
    assign word_addr = PC[11:2];       // Lấy bit [11:2] làm địa chỉ từ
    
    // ========================================================================
    // Đọc lệnh từ bộ nhớ
    // Truy cập đồng bộ theo địa chỉ word_addr
    // ========================================================================
    assign Instruction_Code = memory[word_addr];
    
    // ========================================================================
    // Khởi tạo bộ nhớ từ file hex khi simulation
    // File program.hex chứa các lệnh dạng hex, mỗi dòng 1 lệnh 32-bit
    // ========================================================================
    initial begin
        $readmemh("program.hex", memory);
    end

endmodule

cpu/riscv5stagedemo/IFU/IFU.v
`include "inst_mem.v"
module IFU (
    input wire clock,
    input wire reset,
    
    // Control signals
    input wire pc_src,              // 0: PC+4 (sequential), 1: target_pc (branch/jump)
    input wire stall,               // 1: giữ nguyên PC (pipeline stall)
    
    // Branch/Jump target address
    input wire [31:0] target_pc,    // Địa chỉ nhảy đến
    
    // Outputs
    output reg [31:0] PC_out,       // Current PC
    output wire [31:0] Instruction_Code  // Instruction được fetch
);

    // ========================================================================
    // Program Counter Register
    // ========================================================================
    reg [31:0] PC;
    
    // ========================================================================
    // Next PC Calculation
    // ========================================================================
    wire [31:0] next_pc;
    
    // Logic tính next_pc:
    // - Nếu stall=1: giữ nguyên PC
    // - Nếu pc_src=1: nhảy đến target_pc (branch/jump)
    // - Nếu pc_src=0: PC + 4 (sequential)
    assign next_pc = stall ? PC : 
                     pc_src ? target_pc : 
                     PC + 32'd4;
    
    // ========================================================================
    // Program Counter Update
    // ========================================================================
    always @(posedge clock or posedge reset) begin
        if (reset) begin
            PC <= 32'h00000000;     // Reset PC về địa chỉ 0x00000000
        end
        else begin
            PC <= next_pc;          // Cập nhật PC
        end
    end
    
    // ========================================================================
    // Output Current PC
    // ========================================================================
    always @(*) begin
        PC_out = PC;
    end
    
    // ========================================================================
    // Instruction Memory
    // ========================================================================
    inst_mem inst_memory (
        .PC({PC[31:2],2'b00}),       // Địa chỉ word (chia 4, bỏ 2 bit thấp)
        .Instruction_Code(Instruction_Code)
    );

endmodule

cpu/riscv5stagedemo/IFU/tb_IFU.v
// ============================================================================
// Testbench: IFU_tb - Kiểm tra module IFU (Instruction Fetch Unit)
// Mô tả: Kiểm tra chức năng fetch lệnh, PC update, branch/jump và stall
// ============================================================================

`timescale 1ns/1ps
`include "IFU.v"
module tb_IFU;

    // ========================================================================
    // Tín hiệu testbench
    // ========================================================================
    reg clock;
    reg reset;
    reg pc_src;
    reg stall;
    reg [31:0] target_pc;
    
    wire [31:0] PC_out;
    wire [31:0] Instruction_Code;
    
    // ========================================================================
    // Khởi tạo module IFU
    // ========================================================================
    IFU uut (
        .clock(clock),
        .reset(reset),
        .pc_src(pc_src),
        .stall(stall),
        .target_pc(target_pc),
        .PC_out(PC_out),
        .Instruction_Code(Instruction_Code)
    );
    
    // ========================================================================
    // Tạo xung clock: chu kỳ 10ns (100MHz)
    // ========================================================================
    initial begin
        clock = 0;
        forever #5 clock = ~clock;
    end
    
    // ========================================================================
    // Kịch bản test
    // ========================================================================
    initial begin
        // Tạo file dump để xem sóng
        $dumpfile("tb_IFU.vcd");
        $dumpvars(0, tb_IFU);
        
        // In header
        $display("========================================");
        $display("  IFU Testbench - RISC-V 32IM");
        $display("========================================");
        $display("Time\tPC\t\tInstruction\tMode");
        $display("----------------------------------------");
        
        // Khởi tạo tín hiệu
        reset = 1;
        pc_src = 0;
        stall = 0;
        target_pc = 32'h00000000;
        
        // Test 1: Reset
        #10;
        reset = 0;
        $display("%0t\t0x%h\t0x%h\tReset released", $time, PC_out, Instruction_Code);
        
        // Test 2: Sequential fetch (PC+4)
        $display("\n--- Test Sequential Fetch (PC+4) ---");
        repeat(8) begin
            #10;
            $display("%0t\t0x%h\t0x%h\tSequential", $time, PC_out, Instruction_Code);
        end
        
        // Test 3: Branch/Jump (pc_src = 1)
        $display("\n--- Test Branch to 0x0C ---");
        #10;
        pc_src = 1;
        target_pc = 32'h0000000C;
        #10;
        pc_src = 0;
        $display("%0t\t0x%h\t0x%h\tBranch to 0x0C", $time, PC_out, Instruction_Code);
        
        repeat(3) begin
            #10;
            $display("%0t\t0x%h\t0x%h\tSequential", $time, PC_out, Instruction_Code);
        end
        
        // Test 4: Pipeline Stall
        $display("\n--- Test Pipeline Stall ---");
        #10;
        stall = 1;
        $display("%0t\t0x%h\t0x%h\tStall ON", $time, PC_out, Instruction_Code);
        repeat(3) begin
            #10;
            $display("%0t\t0x%h\t0x%h\tStalled", $time, PC_out, Instruction_Code);
        end
        
        stall = 0;
        #10;
        $display("%0t\t0x%h\t0x%h\tStall OFF", $time, PC_out, Instruction_Code);
        
        // Test 5: Jump to beginning
        $display("\n--- Test Jump to 0x00 ---");
        #10;
        pc_src = 1;
        target_pc = 32'h00000000;
        #10;
        pc_src = 0;
        $display("%0t\t0x%h\t0x%h\tJump to 0x00", $time, PC_out, Instruction_Code);
        
        repeat(4) begin
            #10;
            $display("%0t\t0x%h\t0x%h\tSequential", $time, PC_out, Instruction_Code);
        end
        
        // Test 6: Verify instruction decoding
        $display("\n--- Instruction Verification ---");
        $display("Expected instructions from program.hex:");
        $display("0x00: 0x00000093 - addi x1, x0, 0");
        $display("0x04: 0x00100113 - addi x2, x0, 1");
        $display("0x08: 0x00a00193 - addi x3, x0, 10");
        $display("0x0C: 0x002080b3 - add x1, x1, x2");
        $display("0x10: 0x00110113 - addi x2, x2, 1");
        $display("0x14: 0xfe314ae3 - blt x2, x3, -12");
        $display("0x18: 0x00008513 - addi x10, x1, 0");
        $display("0x1C: 0x00000013 - addi x0, x0, 0 (NOP)");
        
        // Kết thúc simulation
        #50;
        $display("\n========================================");
        $display("  Simulation Complete!");
        $display("========================================");
        $finish;
    end
    
    // ========================================================================
    // Monitor PC changes
    // ========================================================================
    always @(posedge clock) begin
        if (!reset && !stall) begin
            // Có thể thêm check tự động ở đây
        end
    end
    
    // ========================================================================
    // Timeout protection
    // ========================================================================
    initial begin
        #2000;
        $display("ERROR: Simulation timeout!");
        $finish;
    end

endmodule

cpu/riscv5stagedemo/IFU/tb_IFU.vcd
$date
	Mon Nov 03 09:36:35 2025
$end
$version
	Icarus Verilog
$end
$timescale
	1ps
$end
$scope module tb_IFU $end
$var wire 32 ! PC_out [31:0] $end
$var wire 32 " Instruction_Code [31:0] $end
$var reg 1 # clock $end
$var reg 1 $ pc_src $end
$var reg 1 % reset $end
$var reg 1 & stall $end
$var reg 32 ' target_pc [31:0] $end
$scope module uut $end
$var wire 1 # clock $end
$var wire 1 $ pc_src $end
$var wire 1 % reset $end
$var wire 1 & stall $end
$var wire 32 ( target_pc [31:0] $end
$var wire 32 ) next_pc [31:0] $end
$var wire 32 * Instruction_Code [31:0] $end
$var reg 32 + PC [31:0] $end
$var reg 32 , PC_out [31:0] $end
$scope module inst_memory $end
$var wire 32 - Instruction_Code [31:0] $end
$var wire 32 . PC [31:0] $end
$var wire 10 / word_addr [9:0] $end
$upscope $end
$upscope $end
$upscope $end
$enddefinitions $end
$comment Show the parameter values. $end
$dumpall
$end
#0
$dumpvars
b0 /
b0 .
b10010011 -
b0 ,
b0 +
b10010011 *
b100 )
b0 (
b0 '
0&
1%
0$
0#
b10010011 "
b0 !
$end
#5000
1#
#10000
0#
0%
#15000
b1000 )
b100000000000100010011 "
b100000000000100010011 *
b100000000000100010011 -
b1 /
b100 !
b100 ,
b100 .
b100 +
1#
#20000
0#
#25000
b1100 )
b101000000000000110010011 "
b101000000000000110010011 *
b101000000000000110010011 -
b10 /
b1000 !
b1000 ,
b1000 .
b1000 +
1#
#30000
0#
#35000
b10000 )
b1000001000000010110011 "
b1000001000000010110011 *
b1000001000000010110011 -
b11 /
b1100 !
b1100 ,
b1100 .
b1100 +
1#
#40000
0#
#45000
b10100 )
b100010000000100010011 "
b100010000000100010011 *
b100010000000100010011 -
b100 /
b10000 !
b10000 ,
b10000 .
b10000 +
1#
#50000
0#
#55000
b11000 )
b11111110001100010100101011100011 "
b11111110001100010100101011100011 *
b11111110001100010100101011100011 -
b101 /
b10100 !
b10100 ,
b10100 .
b10100 +
1#
#60000
0#
#65000
b11100 )
b1000010100010011 "
b1000010100010011 *
b1000010100010011 -
b110 /
b11000 !
b11000 ,
b11000 .
b11000 +
1#
#70000
0#
#75000
b100000 )
b10011 "
b10011 *
b10011 -
b111 /
b11100 !
b11100 ,
b11100 .
b11100 +
1#
#80000
0#
#85000
b100100 )
bx "
bx *
bx -
b1000 /
b100000 !
b100000 ,
b100000 .
b100000 +
1#
#90000
0#
#95000
b101000 )
b1001 /
b100100 !
b100100 ,
b100100 .
b100100 +
1#
#100000
b1100 )
0#
b1100 '
b1100 (
1$
#105000
b1000001000000010110011 "
b1000001000000010110011 *
b1000001000000010110011 -
b11 /
b1100 !
b1100 ,
b1100 .
b1100 +
1#
#110000
b10000 )
0#
0$
#115000
b10100 )
b100010000000100010011 "
b100010000000100010011 *
b100010000000100010011 -
b100 /
b10000 !
b10000 ,
b10000 .
b10000 +
1#
#120000
0#
#125000
b11000 )
b11111110001100010100101011100011 "
b11111110001100010100101011100011 *
b11111110001100010100101011100011 -
b101 /
b10100 !
b10100 ,
b10100 .
b10100 +
1#
#130000
0#
#135000
b11100 )
b1000010100010011 "
b1000010100010011 *
b1000010100010011 -
b110 /
b11000 !
b11000 ,
b11000 .
b11000 +
1#
#140000
0#
#145000
b100000 )
b10011 "
b10011 *
b10011 -
b111 /
b11100 !
b11100 ,
b11100 .
b11100 +
1#
#150000
b11100 )
0#
1&
#155000
1#
#160000
0#
#165000
1#
#170000
0#
#175000
1#
#180000
b100000 )
0#
0&
#185000
b100100 )
bx "
bx *
bx -
b1000 /
b100000 !
b100000 ,
b100000 .
b100000 +
1#
#190000
0#
#195000
b101000 )
b1001 /
b100100 !
b100100 ,
b100100 .
b100100 +
1#
#200000
b0 )
0#
b0 '
b0 (
1$
#205000
b10010011 "
b10010011 *
b10010011 -
b0 /
b0 !
b0 ,
b0 .
b0 +
1#
#210000
b100 )
0#
0$
#215000
b1000 )
b100000000000100010011 "
b100000000000100010011 *
b100000000000100010011 -
b1 /
b100 !
b100 ,
b100 .
b100 +
1#
#220000
0#
#225000
b1100 )
b101000000000000110010011 "
b101000000000000110010011 *
b101000000000000110010011 -
b10 /
b1000 !
b1000 ,
b1000 .
b1000 +
1#
#230000
0#
#235000
b10000 )
b1000001000000010110011 "
b1000001000000010110011 *
b1000001000000010110011 -
b11 /
b1100 !
b1100 ,
b1100 .
b1100 +
1#
#240000
0#
#245000
b10100 )
b100010000000100010011 "
b100010000000100010011 *
b100010000000100010011 -
b100 /
b10000 !
b10000 ,
b10000 .
b10000 +
1#
#250000
0#
#255000
b11000 )
b11111110001100010100101011100011 "
b11111110001100010100101011100011 *
b11111110001100010100101011100011 -
b101 /
b10100 !
b10100 ,
b10100 .
b10100 +
1#
#260000
0#
#265000
b11100 )
b1000010100010011 "
b1000010100010011 *
b1000010100010011 -
b110 /
b11000 !
b11000 ,
b11000 .
b11000 +
1#
#270000
0#
#275000
b100000 )
b10011 "
b10011 *
b10011 -
b111 /
b11100 !
b11100 ,
b11100 .
b11100 +
1#
#280000
0#
#285000
b100100 )
bx "
bx *
bx -
b1000 /
b100000 !
b100000 ,
b100000 .
b100000 +
1#
#290000
0#
#295000
b101000 )
b1001 /
b100100 !
b100100 ,
b100100 .
b100100 +
1#
