cpu/riscv5stagedemo/REG_FILE/reg_file.v
// ============================================================================
// REG_FILE.v - RISC-V Register File (32 x 32-bit)
// ============================================================================
// Mô tả: Tập 32 thanh ghi, x0 luôn = 0
//        Đọc bất đồng bộ (asynchronous read)
//        Ghi đồng bộ (synchronous write) tại cạnh lên của clock
// ============================================================================

module reg_file (
    input wire clock,
    input wire reset,
    
    // Read ports (asynchronous)
    input wire [4:0] read_reg_num1,      // rs1
    input wire [4:0] read_reg_num2,      // rs2
    output wire [31:0] read_data1,       // dữ liệu từ rs1
    output wire [31:0] read_data2,       // dữ liệu từ rs2
    
    // Write port (synchronous)
    input wire regwrite,                 // enable ghi
    input wire [4:0] write_reg,          // rd
    input wire [31:0] write_data         // dữ liệu ghi vào rd
);

    // Khai báo 32 thanh ghi, mỗi thanh ghi 32-bit
    reg [31:0] registers [31:0];
    
    // Biến để debug (có thể bỏ khi synthesize)
    integer i;
    
    // ========================================================================
    // RESET: Khởi tạo tất cả thanh ghi = 0
    // ========================================================================
    always @(posedge clock or posedge reset) begin
        if (reset) begin
            for (i = 0; i < 32; i = i + 1) begin
                registers[i] <= 32'h00000000;
            end
        end
        else begin
            // ================================================================
            // WRITE: Ghi đồng bộ tại cạnh lên của clock
            // ================================================================
            if (regwrite && (write_reg != 5'b00000)) begin
                registers[write_reg] <= write_data;
            end
            // x0 luôn = 0 (đảm bảo x0 không bao giờ bị ghi đè)
            registers[0] <= 32'h00000000;
        end
    end
    
    // ========================================================================
    // READ: Đọc bất đồng bộ (asynchronous read)
    // ========================================================================
    // x0 luôn trả về 0, các thanh ghi khác trả về giá trị thực
    assign read_data1 = (read_reg_num1 == 5'b00000) ? 32'h00000000 : registers[read_reg_num1];
    assign read_data2 = (read_reg_num2 == 5'b00000) ? 32'h00000000 : registers[read_reg_num2];

endmodule

cpu/riscv5stagedemo/REG_FILE/tb_reg_file.v
// ============================================================================
// REG_FILE_tb.v - Testbench cho RISC-V Register File
// ============================================================================

`timescale 1ns/1ps
`include "reg_file.v"
module tb_reg_file;

    // Tín hiệu clock và reset
    reg clock;
    reg reset;
    
    // Tín hiệu đọc
    reg [4:0] read_reg_num1;
    reg [4:0] read_reg_num2;
    wire [31:0] read_data1;
    wire [31:0] read_data2;
    
    // Tín hiệu ghi
    reg regwrite;
    reg [4:0] write_reg;
    reg [31:0] write_data;
    
    // Khởi tạo DUT (Device Under Test)
    reg_file uut (
        .clock(clock),
        .reset(reset),
        .read_reg_num1(read_reg_num1),
        .read_reg_num2(read_reg_num2),
        .read_data1(read_data1),
        .read_data2(read_data2),
        .regwrite(regwrite),
        .write_reg(write_reg),
        .write_data(write_data)
    );
    
    // Tạo clock 10ns (100MHz)
    initial begin
        clock = 0;
        forever #5 clock = ~clock;
    end
    
    // Test sequence
    initial begin
        // Khởi tạo file dump cho GTKWave
        $dumpfile("tb_reg_file.vcd");
        $dumpvars(0, tb_reg_file);
        
        // Hiển thị header
        $display("============================================");
        $display("  RISC-V Register File Testbench");
        $display("============================================");
        $display("Time\t| Oper\t| Reg\t| Data\t\t| rd1\t\t| rd2");
        $display("--------------------------------------------");
        
        // Khởi tạo tín hiệu
        reset = 1;
        regwrite = 0;
        write_reg = 0;
        write_data = 0;
        read_reg_num1 = 0;
        read_reg_num2 = 0;
        
        // Reset hệ thống
        #20;
        reset = 0;
        #10;
        
        // ================================================================
        // TEST 1: Kiểm tra x0 luôn = 0
        // ================================================================
        $display("\n[TEST 1] Kiểm tra x0 luôn = 0");
        @(posedge clock);
        regwrite = 1;
        write_reg = 5'd0;  // x0
        write_data = 32'hDEADBEEF;
        #1;
        $display("%0t\t| WRITE\t| x%-2d\t| 0x%h\t| -\t\t| -", $time, write_reg, write_data);
        
        @(posedge clock);
        regwrite = 0;
        read_reg_num1 = 5'd0;
        #1;
        $display("%0t\t| READ\t| x%-2d\t| -\t\t| 0x%h\t| -", $time, read_reg_num1, read_data1);
        
        if (read_data1 == 32'h00000000)
            $display("✓ PASS: x0 = 0");
        else
            $display("✗ FAIL: x0 ≠ 0 (got 0x%h)", read_data1);
        
        // ================================================================
        // TEST 2: Ghi và đọc các thanh ghi thông thường
        // ================================================================
        $display("\n[TEST 2] Ghi và đọc thanh ghi x1-x31");
        
        // Ghi vào x1
        @(posedge clock);
        regwrite = 1;
        write_reg = 5'd1;
        write_data = 32'h12345678;
        #1;
        $display("%0t\t| WRITE\t| x%-2d\t| 0x%h\t| -\t\t| -", $time, write_reg, write_data);
        
        // Ghi vào x2
        @(posedge clock);
        write_reg = 5'd2;
        write_data = 32'hABCDEF00;
        #1;
        $display("%0t\t| WRITE\t| x%-2d\t| 0x%h\t| -\t\t| -", $time, write_reg, write_data);
        
        // Ghi vào x31
        @(posedge clock);
        write_reg = 5'd31;
        write_data = 32'hFFFFFFFF;
        #1;
        $display("%0t\t| WRITE\t| x%-2d\t| 0x%h\t| -\t\t| -", $time, write_reg, write_data);
        
        // Đọc x1 và x2
        @(posedge clock);
        regwrite = 0;
        read_reg_num1 = 5'd1;
        read_reg_num2 = 5'd2;
        #1;
        $display("%0t\t| READ\t| x%d,x%d\t| -\t\t| 0x%h\t| 0x%h", 
                 $time, read_reg_num1, read_reg_num2, read_data1, read_data2);
        
        if (read_data1 == 32'h12345678 && read_data2 == 32'hABCDEF00)
            $display("✓ PASS: Đọc x1, x2 đúng");
        else
            $display("✗ FAIL: Đọc sai (x1=0x%h, x2=0x%h)", read_data1, read_data2);
        
        // Đọc x31
        @(posedge clock);
        read_reg_num1 = 5'd31;
        read_reg_num2 = 5'd0;
        #1;
        $display("%0t\t| READ\t| x%d,x%d\t| -\t\t| 0x%h\t| 0x%h", 
                 $time, read_reg_num1, read_reg_num2, read_data1, read_data2);
        
        if (read_data1 == 32'hFFFFFFFF && read_data2 == 32'h00000000)
            $display("✓ PASS: Đọc x31, x0 đúng");
        else
            $display("✗ FAIL: Đọc sai (x31=0x%h, x0=0x%h)", read_data1, read_data2);
        
        // ================================================================
        // TEST 3: Kiểm tra regwrite enable
        // ================================================================
        $display("\n[TEST 3] Kiểm tra regwrite enable");
        
        // Ghi vào x3 với regwrite = 1
        @(posedge clock);
        regwrite = 1;
        write_reg = 5'd3;
        write_data = 32'h11111111;
        #1;
        $display("%0t\t| WRITE\t| x%-2d\t| 0x%h\t| (regwrite=1)", $time, write_reg, write_data);
        
        // Thử ghi vào x3 với regwrite = 0 (không nên ghi)
        @(posedge clock);
        regwrite = 0;
        write_data = 32'h22222222;
        #1;
        $display("%0t\t| WRITE\t| x%-2d\t| 0x%h\t| (regwrite=0)", $time, write_reg, write_data);
        
        // Đọc x3
        @(posedge clock);
        read_reg_num1 = 5'd3;
        #1;
        $display("%0t\t| READ\t| x%-2d\t| -\t\t| 0x%h\t| -", $time, read_reg_num1, read_data1);
        
        if (read_data1 == 32'h11111111)
            $display("✓ PASS: regwrite=0 không ghi được");
        else
            $display("✗ FAIL: regwrite=0 vẫn ghi (got 0x%h)", read_data1);
        
        // ================================================================
        // TEST 4: Đọc bất đồng bộ (asynchronous read)
        // ================================================================
        $display("\n[TEST 4] Kiểm tra đọc bất đồng bộ");
        
        // Ghi vào x10
        @(posedge clock);
        regwrite = 1;
        write_reg = 5'd10;
        write_data = 32'hAAAAAAAA;
        
        // Đọc ngay lập tức (không đợi clock)
        #1;
        read_reg_num1 = 5'd10;
        #1;
        $display("%0t\t| READ\t| x%-2d\t| -\t\t| 0x%h\t| (async)", $time, read_reg_num1, read_data1);
        
        // ================================================================
        // TEST 5: Ghi đồng thời và đọc
        // ================================================================
        $display("\n[TEST 5] Ghi và đọc đồng thời");
        
        @(posedge clock);
        regwrite = 1;
        write_reg = 5'd15;
        write_data = 32'h55555555;
        read_reg_num1 = 5'd15;
        read_reg_num2 = 5'd10;
        #1;
        $display("%0t\t| W+R\t| x%d\t| 0x%h\t| 0x%h\t| 0x%h", 
                 $time, write_reg, write_data, read_data1, read_data2);
        
        // Đọc lại sau khi ghi
        @(posedge clock);
        regwrite = 0;
        #1;
        $display("%0t\t| READ\t| x%d\t| -\t\t| 0x%h\t| 0x%h", 
                 $time, read_reg_num1, read_data1, read_data2);
        
        // ================================================================
        // Kết thúc simulation
        // ================================================================
        #20;
        $display("\n============================================");
        $display("  Testbench hoàn thành!");
        $display("============================================\n");
        $finish;
    end
    
    // Timeout protection
    initial begin
        #1000;
        $display("\n✗ TIMEOUT: Simulation quá lâu!");
        $finish;
    end

endmodule

cpu/riscv5stagedemo/REG_FILE/tb_reg_file.vcd
$date
	Sun Nov 02 13:57:35 2025
$end
$version
	Icarus Verilog
$end
$timescale
	1ps
$end
$scope module tb_reg_file $end
$var wire 32 ! read_data2 [31:0] $end
$var wire 32 " read_data1 [31:0] $end
$var reg 1 # clock $end
$var reg 5 $ read_reg_num1 [4:0] $end
$var reg 5 % read_reg_num2 [4:0] $end
$var reg 1 & regwrite $end
$var reg 1 ' reset $end
$var reg 32 ( write_data [31:0] $end
$var reg 5 ) write_reg [4:0] $end
$scope module uut $end
$var wire 1 # clock $end
$var wire 5 * read_reg_num1 [4:0] $end
$var wire 5 + read_reg_num2 [4:0] $end
$var wire 1 & regwrite $end
$var wire 1 ' reset $end
$var wire 32 , write_data [31:0] $end
$var wire 5 - write_reg [4:0] $end
$var wire 32 . read_data2 [31:0] $end
$var wire 32 / read_data1 [31:0] $end
$var integer 32 0 i [31:0] $end
$upscope $end
$upscope $end
$enddefinitions $end
$comment Show the parameter values. $end
$dumpall
$end
#0
$dumpvars
b100000 0
b0 /
b0 .
b0 -
b0 ,
b0 +
b0 *
b0 )
b0 (
1'
0&
b0 %
b0 $
0#
b0 "
b0 !
$end
#5000
b100000 0
1#
#10000
0#
#15000
b100000 0
1#
#20000
0#
0'
#25000
1#
#30000
0#
#35000
b11011110101011011011111011101111 (
b11011110101011011011111011101111 ,
1&
1#
#40000
0#
#45000
0&
1#
#50000
0#
#55000
b10010001101000101011001111000 (
b10010001101000101011001111000 ,
b1 )
b1 -
1&
1#
#60000
0#
#65000
b10101011110011011110111100000000 (
b10101011110011011110111100000000 ,
b10 )
b10 -
1#
#70000
0#
#75000
b11111111111111111111111111111111 (
b11111111111111111111111111111111 ,
b11111 )
b11111 -
1#
#80000
0#
#85000
b10101011110011011110111100000000 !
b10101011110011011110111100000000 .
b10010001101000101011001111000 "
b10010001101000101011001111000 /
b10 %
b10 +
b1 $
b1 *
0&
1#
#90000
0#
#95000
b0 !
b0 .
b11111111111111111111111111111111 "
b11111111111111111111111111111111 /
b0 %
b0 +
b11111 $
b11111 *
1#
#100000
0#
#105000
b10001000100010001000100010001 (
b10001000100010001000100010001 ,
b11 )
b11 -
1&
1#
#110000
0#
#115000
b100010001000100010001000100010 (
b100010001000100010001000100010 ,
0&
1#
#120000
0#
#125000
b10001000100010001000100010001 "
b10001000100010001000100010001 /
b11 $
b11 *
1#
#130000
0#
#135000
b10101010101010101010101010101010 (
b10101010101010101010101010101010 ,
b1010 )
b1010 -
1&
1#
#136000
b10101010101010101010101010101010 "
b10101010101010101010101010101010 /
b1010 $
b1010 *
#140000
0#
#145000
b10101010101010101010101010101010 !
b10101010101010101010101010101010 .
b1010101010101010101010101010101 "
b1010101010101010101010101010101 /
b1010 %
b1010 +
b1111 $
b1111 *
b1010101010101010101010101010101 (
b1010101010101010101010101010101 ,
b1111 )
b1111 -
1#
#150000
0#
#155000
0&
1#
